pydpc
